rtl/alu.sv
// alu.sv
// The ALU (Arithmetic Logic Unit) performs all computation in the CPU.
// It's purely combinational -- no clock, inputs in -> result out immediately.
// The control unit (built later) will tell it which operation to perform
// via alu_ctrl. For now we support the operations our 6-instruction ISA needs.

module alu (
    input  logic [31:0] a,          // first operand (always from rs1)
    input  logic [31:0] b,          // second operand (rs2 or immediate)
    input  logic [2:0]  alu_ctrl,   // which operation to perform
    output logic [31:0] result,     // computed result
    output logic        zero        // 1 if result == 0, used by BEQ
);

    // ALU operation encoding -- we'll use these same codes in the
    // control unit later when decoding instructions
    localparam ALU_ADD  = 3'b000;   // ADD, ADDI, LW, SW (address calc)
    localparam ALU_SUB  = 3'b001;   // SUB
    localparam ALU_AND  = 3'b010;   // AND (useful later, cheap to add now)
    localparam ALU_OR   = 3'b011;   // OR  (same)
    localparam ALU_SLT  = 3'b100;   // Set Less Than (needed for some branches)

    always_comb begin
        case (alu_ctrl)
            ALU_ADD:  result = a + b;
            ALU_SUB:  result = a - b;
            ALU_AND:  result = a & b;
            ALU_OR:   result = a | b;
            ALU_SLT:  result = ($signed(a) < $signed(b)) ? 32'd1 : 32'd0;
            default:  result = 32'b0;
        endcase
    end

    // Zero flag -- BEQ works by subtracting rs1-rs2 and checking if result==0
    assign zero = (result == 32'b0);

endmodule

tb/tb_alu.sv
// tb_alu.sv
// Tests every ALU operation, including edge cases that matter:
// overflow behavior, signed comparison, and the zero flag.

`timescale 1ns/1ps

module tb_alu;

    logic [31:0] a, b, result;
    logic [2:0]  alu_ctrl;
    logic        zero;

    alu dut (
        .a(a),
        .b(b),
        .alu_ctrl(alu_ctrl),
        .result(result),
        .zero(zero)
    );

    // Task to check a result and print PASS/FAIL
    task check;
        input [31:0] expected;
        input string test_name;
        if (result == expected)
            $display("PASS: %s => %0d", test_name, result);
        else
            $display("FAIL: %s => expected %0d, got %0d", test_name, expected, result);
    endtask

    initial begin
        $dumpfile("alu.vcd");
        $dumpvars(0, tb_alu);

        // ADD
        alu_ctrl = 3'b000; a = 32'd10;  b = 32'd5;  #1; check(32'd15,  "ADD 10+5");
        alu_ctrl = 3'b000; a = 32'd0;   b = 32'd0;  #1; check(32'd0,   "ADD 0+0");

        // SUB
        alu_ctrl = 3'b001; a = 32'd10;  b = 32'd3;  #1; check(32'd7,   "SUB 10-3");
        alu_ctrl = 3'b001; a = 32'd5;   b = 32'd5;  #1; check(32'd0,   "SUB 5-5 (zero flag test)");

        // Zero flag -- critical for BEQ
        // BEQ does rs1-rs2, branches if zero=1
        if (zero == 1'b1)
            $display("PASS: zero flag set correctly when result=0");
        else
            $display("FAIL: zero flag should be 1 when result=0");

        alu_ctrl = 3'b001; a = 32'd10;  b = 32'd3;  #1;
        if (zero == 1'b0)
            $display("PASS: zero flag clear when result!=0");
        else
            $display("FAIL: zero flag should be 0 when result!=0");

        // AND
        alu_ctrl = 3'b010; a = 32'hFF00FF00; b = 32'h0F0F0F0F; #1;
        check(32'h0F000F00, "AND");

        // OR
        alu_ctrl = 3'b011; a = 32'hFF000000; b = 32'h00FF0000; #1;
        check(32'hFFFF0000, "OR");

        // SLT (signed less than) -- 
        // -1 in two's complement is 32'hFFFFFFFF, which is > 1 unsigned
        // but < 1 signed. SLT should correctly treat it as signed.
        alu_ctrl = 3'b100; a = 32'hFFFFFFFF; b = 32'd1; #1;
        check(32'd1, "SLT: -1 < 1 (signed)");

        alu_ctrl = 3'b100; a = 32'd5; b = 32'd3; #1;
        check(32'd0, "SLT: 5 not < 3");

        // ADDI behaves identically to ADD from the ALU's perspective --
        // the difference is that b comes from an immediate, not a register.
        // The control unit handles that distinction, not the ALU.
        alu_ctrl = 3'b000; a = 32'd100; b = 32'd1; #1;
        check(32'd101, "ADDI equivalent: 100+1");

        $finish;
    end

endmodule

alu.vcd
$date
	Fri Jun 26 14:50:45 2026
$end
$version
	Icarus Verilog
$end
$timescale
	1ps
$end
$scope module tb_alu $end
$var wire 1 ! zero $end
$var wire 32 " result [31:0] $end
$var reg 32 # a [31:0] $end
$var reg 3 $ alu_ctrl [2:0] $end
$var reg 32 % b [31:0] $end
$scope module dut $end
$var wire 32 & a [31:0] $end
$var wire 3 ' alu_ctrl [2:0] $end
$var wire 32 ( b [31:0] $end
$var wire 1 ! zero $end
$var parameter 3 ) ALU_ADD $end
$var parameter 3 * ALU_AND $end
$var parameter 3 + ALU_OR $end
$var parameter 3 , ALU_SLT $end
$var parameter 3 - ALU_SUB $end
$var reg 32 . result [31:0] $end
$upscope $end
$scope task check $end
$var reg 32 / expected [31:0] $end
$upscope $end
$upscope $end
$enddefinitions $end
$comment Show the parameter values. $end
$dumpall
b1 -
b100 ,
b11 +
b10 *
b0 )
$end
#0
$dumpvars
bx /
b1111 .
b101 (
b0 '
b1010 &
b101 %
b0 $
b1010 #
b1111 "
0!
$end
#1000
1!
b0 "
b0 .
b0 %
b0 (
b0 #
b0 &
b1111 /
#2000
0!
b111 "
b111 .
b11 %
b11 (
b1010 #
b1010 &
b1 $
b1 '
b0 /
#3000
1!
b0 "
b0 .
b101 %
b101 (
b101 #
b101 &
b111 /
#4000
0!
b111 "
b111 .
b11 %
b11 (
b1010 #
b1010 &
b0 /
#5000
b1111000000000000111100000000 "
b1111000000000000111100000000 .
b1111000011110000111100001111 %
b1111000011110000111100001111 (
b11111111000000001111111100000000 #
b11111111000000001111111100000000 &
b10 $
b10 '
#6000
b11111111111111110000000000000000 "
b11111111111111110000000000000000 .
b111111110000000000000000 %
b111111110000000000000000 (
b11111111000000000000000000000000 #
b11111111000000000000000000000000 &
b11 $
b11 '
b1111000000000000111100000000 /
#7000
b1 "
b1 .
b1 %
b1 (
b11111111111111111111111111111111 #
b11111111111111111111111111111111 &
b100 $
b100 '
b11111111111111110000000000000000 /
#8000
1!
b0 "
b0 .
b11 %
b11 (
b101 #
b101 &
b1 /
#9000
0!
b1100101 "
b1100101 .
b1 %
b1 (
b1100100 #
b1100100 &
b0 $
b0 '
b0 /
#10000
b1100101 /
