rtl/dmem.sv
// dmem.sv
// Data memory -- used by LW (load word) and SW (store word) instructions.
// Unlike imem (read-only), this memory supports both reads and writes.
//
// Read is combinational (address in, data out same cycle) so the MEM
// stage can use the loaded value immediately. Write is synchronous
// (happens on clock edge), same pattern as the register file write port.

module dmem (
    input  logic        clk,
    input  logic        we,          // write enable (1 for SW, 0 otherwise)
    input  logic [31:0] addr,        // byte address to read/write
    input  logic [31:0] write_data,  // data to store (for SW)
    output logic [31:0] read_data    // data loaded (for LW)
);

    // 64 words of data memory -- plenty for our test programs
    logic [31:0] mem [0:63];

    initial begin
        for (int i = 0; i < 64; i++) begin
            mem[i] = 32'b0;
        end
    end

    // Synchronous write -- happens on the clock edge, same as regfile
    always_ff @(posedge clk) begin
        if (we) begin
            mem[addr[7:2]] <= write_data;
        end
    end

    // Combinational read -- LW needs the value available within the
    // same MEM stage cycle, no waiting for a clock edge
    assign read_data = mem[addr[7:2]];

endmodule

tb/tb_dmem.sv
// tb_dmem.sv
// Tests data memory read/write behavior. Key things to verify:
// 1. Writes only happen when we=1, and only on the clock edge
// 2. Reads are combinational -- value available without waiting for clk
// 3. Writing to one address doesn't affect others

`timescale 1ns/1ps

module tb_dmem;

    logic        clk;
    logic        we;
    logic [31:0] addr, write_data, read_data;

    dmem dut (
        .clk(clk),
        .we(we),
        .addr(addr),
        .write_data(write_data),
        .read_data(read_data)
    );

    always begin
        clk = 0; #5;
        clk = 1; #5;
    end

    initial begin
        $dumpfile("dmem.vcd");
        $dumpvars(0, tb_dmem);

        // Test 1: write 77 to address 0, then read it back
        we = 1; addr = 32'd0; write_data = 32'd77;
        @(posedge clk);
        #1;
        we = 0;
        #1;
        if (read_data == 32'd77)
            $display("PASS: wrote 77 to addr 0, read back %0d", read_data);
        else
            $display("FAIL: expected 77, got %0d", read_data);

        // Test 2: write to a different address, confirm addr 0 unchanged
        we = 1; addr = 32'd4; write_data = 32'd200;
        @(posedge clk);
        #1;
        we = 0; addr = 32'd0;
        #1;
        if (read_data == 32'd77)
            $display("PASS: addr 0 still holds 77 after writing addr 4");
        else
            $display("FAIL: addr 0 corrupted, got %0d", read_data);

        addr = 32'd4;
        #1;
        if (read_data == 32'd200)
            $display("PASS: addr 4 holds 200 correctly");
        else
            $display("FAIL: addr 4 expected 200, got %0d", read_data);

        // Test 3: with we=0, writing shouldn't happen even if write_data changes
        we = 0; addr = 32'd8; write_data = 32'd999;
        @(posedge clk);
        #1;
        if (read_data == 32'd0)
            $display("PASS: addr 8 unwritten (we=0 correctly blocked write)");
        else
            $display("FAIL: addr 8 should be 0, got %0d", read_data);

        $finish;
    end

endmodule

dmem.vcd
$date
	Mon Jun 29 23:40:07 2026
$end
$version
	Icarus Verilog
$end
$timescale
	1ps
$end
$scope module tb_dmem $end
$var wire 32 ! read_data [31:0] $end
$var reg 32 " addr [31:0] $end
$var reg 1 # clk $end
$var reg 1 $ we $end
$var reg 32 % write_data [31:0] $end
$scope module dut $end
$var wire 32 & addr [31:0] $end
$var wire 1 # clk $end
$var wire 32 ' read_data [31:0] $end
$var wire 1 $ we $end
$var wire 32 ( write_data [31:0] $end
$scope begin $ivl_for_loop0 $end
$var integer 32 ) i [31:0] $end
$upscope $end
$upscope $end
$upscope $end
$enddefinitions $end
$comment Show the parameter values. $end
$dumpall
$end
#0
$dumpvars
b1000000 )
b1001101 (
b0 '
b0 &
b1001101 %
1$
0#
b0 "
b0 !
$end
#5000
b1001101 !
b1001101 '
1#
#6000
0$
#7000
b0 !
b0 '
b11001000 %
b11001000 (
b100 "
b100 &
1$
#10000
0#
#15000
b11001000 !
b11001000 '
1#
#16000
b1001101 !
b1001101 '
b0 "
b0 &
0$
#17000
b11001000 !
b11001000 '
b100 "
b100 &
#18000
b0 !
b0 '
b1111100111 %
b1111100111 (
b1000 "
b1000 &
